pypi_insiders-1.1.0.dist-info/METADATA
pypi_insiders-1.1.0.dist-info/WHEEL
pypi_insiders-1.1.0.dist-info/entry_points.txt
pypi_insiders-1.1.0.dist-info/licenses/LICENSE
pypi_insiders/__init__.py
pypi_insiders/__main__.py
pypi_insiders/cli/__init__.py
pypi_insiders/cli/repos.py
pypi_insiders/cli/server.py
pypi_insiders/cli/update.py
pypi_insiders/cli/watcher.py
pypi_insiders/debug.py
pypi_insiders/defaults.py
pypi_insiders/logger.py
pypi_insiders/py.typed
pypi_insiders/repos.py
pypi_insiders/server.py
pypi_insiders/update.py
pypi_insiders/watcher.py
pypi_insiders-1.1.0.dist-info/RECORD
