Metadata-Version: 2.1
Name: pypi-insiders
Version: 1.1.0
Summary: Self-hosted PyPI server with automatic updates for Insiders versions of projects.
Author-Email: =?utf-8?q?Timoth=C3=A9e_Mazzucotelli?= <dev@pawamoy.fr>
License: ISC
Classifier: Development Status :: 4 - Beta
Classifier: Intended Audience :: Developers
Classifier: Programming Language :: Python
Classifier: Programming Language :: Python :: 3
Classifier: Programming Language :: Python :: 3 :: Only
Classifier: Programming Language :: Python :: 3.10
Classifier: Programming Language :: Python :: 3.11
Classifier: Programming Language :: Python :: 3.12
Classifier: Programming Language :: Python :: 3.13
Classifier: Programming Language :: Python :: 3.14
Classifier: Topic :: Software Development
Classifier: Topic :: Utilities
Classifier: Typing :: Typed
Project-URL: Homepage, https://pawamoy.github.io/pypi-insiders
Project-URL: Documentation, https://pawamoy.github.io/pypi-insiders
Project-URL: Changelog, https://pawamoy.github.io/pypi-insiders/changelog
Project-URL: Repository, https://github.com/pawamoy/pypi-insiders
Project-URL: Issues, https://github.com/pawamoy/pypi-insiders/issues
Project-URL: Discussions, https://github.com/pawamoy/pypi-insiders/discussions
Project-URL: Gitter, https://gitter.im/pypi-insiders/community
Project-URL: Funding, https://github.com/sponsors/pawamoy
Requires-Python: >=3.10
Requires-Dist: build>=0.10
Requires-Dist: failprint>=1.0
Requires-Dist: loguru>=0.7
Requires-Dist: packaging>=23.1
Requires-Dist: platformdirs>=3.5
Requires-Dist: psutil>=5.9
Requires-Dist: pypiserver>=1.5
Requires-Dist: twine>=4.0
Requires-Dist: unearth>=0.9
